numeripy/__init__.py
numeripy/post_processing.py
numeripy/ODE_solvers/Adam_Bashforth.py
numeripy/ODE_solvers/Euler.py
numeripy/ODE_solvers/FD_BVP.py
numeripy/ODE_solvers/Modified_Euler.py
numeripy/ODE_solvers/Predictor_Corrector.py
numeripy/ODE_solvers/RK.py
numeripy/ODE_solvers/RKF.py
numeripy/ODE_solvers/Taylor.py
numeripy/ODE_solvers/__init__.py
numeripy/ODE_solvers/help.py
numeripy/PDE_FD/__init__.py
numeripy/PDE_FD/finite_diff.py
numeripy/PDE_FD/help.py
numeripy/matrix_methods/__init__.py
numeripy/matrix_methods/factorization.py
numeripy/matrix_methods/gebs.py
numeripy/matrix_methods/help.py
numeripy/matrix_methods/iterative.py
numeripy/matrix_methods/matrix.py
numeripy-0.1.6.dist-info/licenses/LICENSE
numeripy-0.1.6.dist-info/METADATA
numeripy-0.1.6.dist-info/WHEEL
numeripy-0.1.6.dist-info/top_level.txt
numeripy-0.1.6.dist-info/RECORD
